fitz/__init__.pyi
fitz/py.typed
pymupdf/__init__.pyi
pymupdf/py.typed
pymupdf/table.pyi
pymupdf_stubs-1.26.1.post1.dist-info/METADATA
pymupdf_stubs-1.26.1.post1.dist-info/WHEEL
pymupdf_stubs-1.26.1.post1.dist-info/licenses/LICENSE
pymupdf_stubs-1.26.1.post1.dist-info/RECORD
