Metadata-Version: 2.4
Name: pymupdf-stubs
Version: 1.26.1.post1
Summary: Type stubs for PyMuPDF (fitz), automatically generated
Project-URL: Homepage, https://github.com/elohmeier/pymupdf-stubs
Project-URL: Repository, https://github.com/elohmeier/pymupdf-stubs
Project-URL: Issues, https://github.com/elohmeier/pymupdf-stubs/issues
Project-URL: PyMuPDF, https://github.com/pymupdf/PyMuPDF
Author-email: Enno Richter <enno@nerdworks.de>
License: Apache-2.0
License-File: LICENSE
Keywords: fitz,mupdf,mypy,pdf,pymupdf,stubs,type hints,typing
Classifier: Development Status :: 4 - Beta
Classifier: Environment :: Console
Classifier: Intended Audience :: Developers
Classifier: License :: OSI Approved :: Apache Software License
Classifier: Operating System :: OS Independent
Classifier: Programming Language :: Python :: 3
Classifier: Programming Language :: Python :: 3.8
Classifier: Programming Language :: Python :: 3.9
Classifier: Programming Language :: Python :: 3.10
Classifier: Programming Language :: Python :: 3.11
Classifier: Programming Language :: Python :: 3.12
Classifier: Topic :: Software Development :: Libraries :: Python Modules
Classifier: Topic :: Utilities
Classifier: Typing :: Stubs Only
Requires-Python: >=3.12
Requires-Dist: pymupdf<1.27.0,>=1.26.1
